pyunit_newword/__init__.py
pyunit_newword/auto.txt
pyunit_newword/words.py
pyunit_newword-2020.2.12.dist-info/METADATA
pyunit_newword-2020.2.12.dist-info/WHEEL
pyunit_newword-2020.2.12.dist-info/top_level.txt
pyunit_newword-2020.2.12.dist-info/zip-safe
pyunit_newword-2020.2.12.dist-info/RECORD
