Metadata-Version: 2.1
Name: pyunit-newword
Version: 2020.2.12
Summary: 新词发现算法
Home-page: https://github.com/PyUnit/pyunit-newword
Author: Jtyoui
Author-email: jtyoui@qq.com
License: MIT Licence
Platform: any
Classifier: Programming Language :: Python :: 3
Classifier: License :: OSI Approved :: MIT License
Classifier: Operating System :: OS Independent
Requires-Dist: joblib (==0.14.1)
Requires-Dist: numpy (==1.18.1)
Requires-Dist: scikit-learn (==0.22.1)
Requires-Dist: scipy (==1.4.1)
Requires-Dist: sklearn (==0.0)
Requires-Dist: tqdm (==4.42.1)
